setup.py
isbnlib_bol/__init__.py
isbnlib_bol/_bol.py
isbnlib_bol.egg-info/PKG-INFO
isbnlib_bol.egg-info/SOURCES.txt
isbnlib_bol.egg-info/dependency_links.txt
isbnlib_bol.egg-info/entry_points.txt
isbnlib_bol.egg-info/requires.txt
isbnlib_bol.egg-info/top_level.txt