Metadata-Version: 1.0
Name: isbnlib-bol
Version: 1.0.3
Summary: ISBN lookup for Bol.com
Home-page: https://git.finetuned.nl/stan/isbnlib-bol
Author: Stan Janssen
Author-email: pypi@finetuned.nl
License: UNKNOWN
Platform: UNKNOWN
